plone.app.customerize-2.0.3-py3.13-nspkg.pth
plone/app/customerize/README.txt
plone/app/customerize/TODO.txt
plone/app/customerize/__init__.py
plone/app/customerize/browser.py
plone/app/customerize/configure.zcml
plone/app/customerize/customize.pt
plone/app/customerize/dependencies.zcml
plone/app/customerize/registration.py
plone/app/customerize/registrations.pt
plone/app/customerize/testing.py
plone/app/customerize/tool.gif
plone/app/customerize/tool.py
plone/app/customerize/tests/__init__.py
plone/app/customerize/tests/duplicate_viewlet.zcml
plone/app/customerize/tests/interfaces.py
plone/app/customerize/tests/local.pt
plone/app/customerize/tests/standard.pt
plone/app/customerize/tests/testBrowserLayers.txt
plone/app/customerize/tests/testCustomizeView.txt
plone/app/customerize/tests/testDocTests.py
plone/app/customerize/tests/testing.zcml
plone/app/customerize/tests/viewlets.py
plone/app/customerize/tests/profiles/testing/viewlets.xml
plone_app_customerize-2.0.3.dist-info/METADATA
plone_app_customerize-2.0.3.dist-info/WHEEL
plone_app_customerize-2.0.3.dist-info/namespace_packages.txt
plone_app_customerize-2.0.3.dist-info/top_level.txt
plone_app_customerize-2.0.3.dist-info/RECORD
